rtl/comparator.v
// Comparator needs to :
// 1. Compare two numbers, one is the input and the other is a threshold value
// 2. Output 1 if the first number is greater than the second, otherwise output 0
// Value: inputs for v_in, v_ref, hyst etc, outputs fault signal
// Vin, Vref, Hyst, Vout
module comparator #(
    parameter WIDTH = 8
)(
    input wire [WIDTH-1:0] v_in,
    input wire [WIDTH-1:0] v_ref,
    input wire [WIDTH-1:0] hyst,
    input wire             clk,
    input wire             rst_n,
    output reg             fault
);


always @(posedge clk or negedge rst_n) begin
    if (!rst_n) begin // reset state
        fault <= 1'b0;                      // fault recovery forced
    end else begin // non-reset state
        if (fault) begin // fault present
            if (v_in < (v_ref - hyst)) begin
                fault <= 1'b0;              // fault recovered naturally
            end
        end else begin // fault = 0
            if (v_in >= (v_ref)) begin
                fault <= 1'b1;              // fault asserted
            end
        end
    end
end

endmodule

tb/tb_comparator.v
`timescale 1ns/1ps

module tb_comparator;

    // signals to connect to DUT (devide under test)
    reg clk, rst_n;
    reg [7:0] v_in, v_ref, hyst;
    wire fault;

    // instantiate comparator
    comparator #(.WIDTH(8)) DUT (
        .clk   ( clk   ),
        .rst_n ( rst_n ),
        .v_in  ( v_in  ),
        .v_ref ( v_ref ),
        .hyst  ( hyst  ),
        .fault ( fault )
    );

    initial clk = 0;
    always #5 clk = ~clk; // toggle every 5ns, 10ns period, 100MHz freq

    // GTKWave dependencies (waveforms)
    initial begin
        $dumpfile ( "tb_comparator.vcd" );
        $dumpvars ( 0, tb_comparator    );
    end

    initial begin
        rst_n = 1'b0; // initializing
        v_in = 8'd0;
        v_ref = 8'd0;
        hyst = 8'd0;

        // let 200 represent 400mV

        #20 rst_n = 1'b1; // releasing reset
        #10 v_ref = 8'd200; // 400mV lets say
        #10 hyst = 8'd20; // 40mV lets say

        // safe v_in vals
        #10 v_in = 8'd50;
        #10 v_in = 8'd75;
        #20 v_in = 8'd199;

        // unsafe v_in vals
        #10 v_in = 8'd200;
        #22 v_in = 8'd201;

        // v_in hasn't recovered under hyst threshold
        #10 v_in = 8'd190;
        #10 v_in = 8'd185;
        #10 v_in = 8'd180;

        // v_in recovers
        #20 v_in = 8'd179;
        #20 v_in = 8'd70;

        // quick reset force check
        #20 v_in = 8'd220;
        #25 rst_n = 1'b0;
        #20 rst_n = 1'b1;  // now this should cause fault to reassert
        #20 v_in = 8'd150;
        #20 v_in = 8'd145;

        $finish;
    end

endmodule

tb_comparator.vcd
$date
	Wed May 20 17:09:15 2026
$end
$version
	Icarus Verilog
$end
$timescale
	1ps
$end
$scope module tb_comparator $end
$var wire 1 ! fault $end
$var reg 1 " clk $end
$var reg 8 # hyst [7:0] $end
$var reg 1 $ rst_n $end
$var reg 8 % v_in [7:0] $end
$var reg 8 & v_ref [7:0] $end
$scope module DUT $end
$var wire 1 " clk $end
$var wire 8 ' hyst [7:0] $end
$var wire 1 $ rst_n $end
$var wire 8 ( v_in [7:0] $end
$var wire 8 ) v_ref [7:0] $end
$var parameter 32 * WIDTH $end
$var reg 1 ! fault $end
$upscope $end
$upscope $end
$enddefinitions $end
$comment Show the parameter values. $end
$dumpall
b1000 *
$end
#0
$dumpvars
b0 )
b0 (
b0 '
b0 &
b0 %
0$
b0 #
0"
0!
$end
#5000
1"
#10000
0"
#15000
1"
#20000
0"
1$
#25000
1!
1"
#30000
0"
b11001000 &
b11001000 )
#35000
0!
1"
#40000
0"
b10100 #
b10100 '
#45000
1"
#50000
0"
b110010 %
b110010 (
#55000
1"
#60000
0"
b1001011 %
b1001011 (
#65000
1"
#70000
0"
#75000
1"
#80000
0"
b11000111 %
b11000111 (
#85000
1"
#90000
0"
b11001000 %
b11001000 (
#95000
1!
1"
#100000
0"
#105000
1"
#110000
0"
#112000
b11001001 %
b11001001 (
#115000
1"
#120000
0"
#122000
b10111110 %
b10111110 (
#125000
1"
#130000
0"
#132000
b10111001 %
b10111001 (
#135000
1"
#140000
0"
#142000
b10110100 %
b10110100 (
#145000
1"
#150000
0"
#155000
1"
#160000
0"
#162000
b10110011 %
b10110011 (
#165000
0!
1"
#170000
0"
#175000
1"
#180000
0"
#182000
b1000110 %
b1000110 (
#185000
1"
#190000
0"
#195000
1"
#200000
0"
#202000
b11011100 %
b11011100 (
#205000
1!
1"
#210000
0"
#215000
1"
#220000
0"
#225000
1"
#227000
0!
0$
#230000
0"
#235000
1"
#240000
0"
#245000
1"
#247000
1$
#250000
0"
#255000
1!
1"
#260000
0"
#265000
1"
#267000
b10010110 %
b10010110 (
#270000
0"
#275000
0!
1"
#280000
0"
#285000
1"
#287000
b10010001 %
b10010001 (
