rtl/wd_timer.v
// inputs:  clk, rst_n, edge_pulse, timeout_cfg [15:0]
// outputs: hb_fault
// takes edge_pulse from edge_detect and outputs hb_fault to the FSM. 
// Conceptually just a counter that resets on every pulse and faults when it times out.

module wd_timer #(
    parameter WIDTH = 16

)(
    input wire              clk,
    input wire              rst_n,
    input wire              edge_pulse,
    input wire  [WIDTH-1:0] timeout_cfg,
    output reg              hb_fault
);

reg [WIDTH-1:0] count;

always @(posedge clk or negedge rst_n ) begin
    if (!rst_n) begin
        count <= 0;
        hb_fault <= 1'b0;
    end else begin
        if (edge_pulse) begin
            count <= 0;
            hb_fault <= 1'b0;
        end else begin
            count <= count + 1;
            hb_fault <= (count >= timeout_cfg);
        end
    end
end

endmodule

tb/tb_wd_timer.v
`timescale 1ns/1ps

module tb_wd_timer;

    // signals to connect to DUT
    reg         clk, rst_n;
    reg         edge_pulse;
    reg  [15:0] timeout_cfg;
    wire        hb_fault;

    // instantiate wd_timer
    wd_timer #(.WIDTH(16)) DUT (
        .clk         (clk),
        .rst_n       (rst_n),
        .edge_pulse  (edge_pulse),
        .timeout_cfg (timeout_cfg),
        .hb_fault    (hb_fault)
    );

    initial clk = 0;
    always #5 clk = ~clk; // 10ns period, 100MHz

    initial begin
        $dumpfile("tb_wd_timer.vcd");
        $dumpvars(0, tb_wd_timer);
    end

    initial begin
        rst_n      = 1'b0;
        edge_pulse = 1'b0;
        timeout_cfg = 16'd10; // small timeout for simulation

        #20 rst_n = 1'b1; // release reset

        // healthy heartbeat — pulse before timeout, hb_fault stays low
        #30 edge_pulse = 1'b1;
        #10 edge_pulse = 1'b0;
        #30 edge_pulse = 1'b1; // pulse again before timeout
        #10 edge_pulse = 1'b0;
        #30 edge_pulse = 1'b1;
        #10 edge_pulse = 1'b0;
        #30;

        // missing heartbeat — no pulse, counter runs to timeout
        // hb_fault should assert after 10 cycles
        #200;

        // heartbeat resumes — edge_pulse resets counter, hb_fault clears
        edge_pulse = 1'b1;
        #10 edge_pulse = 1'b0;
        #30;

        // change timeout_cfg to longer window
        timeout_cfg = 16'd20;
        #30 edge_pulse = 1'b1;
        #10 edge_pulse = 1'b0;
        #150; // 15 cycles — under new threshold, no fault
        edge_pulse = 1'b1;
        #10 edge_pulse = 1'b0;
        #30;

        // reset during fault
        #200; // let fault assert
        rst_n = 1'b0;
        #20 rst_n = 1'b1; // hb_fault should clear
        #30;

        $finish;
    end

endmodule

tb_wd_timer.vcd
$date
	Sat May 23 11:32:18 2026
$end
$version
	Icarus Verilog
$end
$timescale
	1ps
$end
$scope module tb_wd_timer $end
$var wire 1 ! hb_fault $end
$var reg 1 " clk $end
$var reg 1 # edge_pulse $end
$var reg 1 $ rst_n $end
$var reg 16 % timeout_cfg [15:0] $end
$scope module DUT $end
$var wire 1 " clk $end
$var wire 1 # edge_pulse $end
$var wire 1 $ rst_n $end
$var wire 16 & timeout_cfg [15:0] $end
$var parameter 32 ' WIDTH $end
$var reg 16 ( count [15:0] $end
$var reg 1 ! hb_fault $end
$upscope $end
$upscope $end
$enddefinitions $end
$comment Show the parameter values. $end
$dumpall
b10000 '
$end
#0
$dumpvars
b0 (
b1010 &
b1010 %
0$
0#
0"
0!
$end
#5000
1"
#10000
0"
#15000
1"
#20000
0"
1$
#25000
b1 (
1"
#30000
0"
#35000
b10 (
1"
#40000
0"
#45000
b11 (
1"
#50000
0"
1#
#55000
b0 (
1"
#60000
0"
0#
#65000
b1 (
1"
#70000
0"
#75000
b10 (
1"
#80000
0"
#85000
b11 (
1"
#90000
0"
1#
#95000
b0 (
1"
#100000
0"
0#
#105000
b1 (
1"
#110000
0"
#115000
b10 (
1"
#120000
0"
#125000
b11 (
1"
#130000
0"
1#
#135000
b0 (
1"
#140000
0"
0#
#145000
b1 (
1"
#150000
0"
#155000
b10 (
1"
#160000
0"
#165000
b11 (
1"
#170000
0"
#175000
b100 (
1"
#180000
0"
#185000
b101 (
1"
#190000
0"
#195000
b110 (
1"
#200000
0"
#205000
b111 (
1"
#210000
0"
#215000
b1000 (
1"
#220000
0"
#225000
b1001 (
1"
#230000
0"
#235000
b1010 (
1"
#240000
0"
#245000
1!
b1011 (
1"
#250000
0"
#255000
b1100 (
1"
#260000
0"
#265000
b1101 (
1"
#270000
0"
#275000
b1110 (
1"
#280000
0"
#285000
b1111 (
1"
#290000
0"
#295000
b10000 (
1"
#300000
0"
#305000
b10001 (
1"
#310000
0"
#315000
b10010 (
1"
#320000
0"
#325000
b10011 (
1"
#330000
0"
#335000
b10100 (
1"
#340000
0"
#345000
b10101 (
1"
#350000
0"
#355000
b10110 (
1"
#360000
0"
#365000
b10111 (
1"
#370000
0"
1#
#375000
0!
b0 (
1"
#380000
0"
0#
#385000
b1 (
1"
#390000
0"
#395000
b10 (
1"
#400000
0"
#405000
b11 (
1"
#410000
0"
b10100 %
b10100 &
#415000
b100 (
1"
#420000
0"
#425000
b101 (
1"
#430000
0"
#435000
b110 (
1"
#440000
0"
1#
#445000
b0 (
1"
#450000
0"
0#
#455000
b1 (
1"
#460000
0"
#465000
b10 (
1"
#470000
0"
#475000
b11 (
1"
#480000
0"
#485000
b100 (
1"
#490000
0"
#495000
b101 (
1"
#500000
0"
#505000
b110 (
1"
#510000
0"
#515000
b111 (
1"
#520000
0"
#525000
b1000 (
1"
#530000
0"
#535000
b1001 (
1"
#540000
0"
#545000
b1010 (
1"
#550000
0"
#555000
b1011 (
1"
#560000
0"
#565000
b1100 (
1"
#570000
0"
#575000
b1101 (
1"
#580000
0"
#585000
b1110 (
1"
#590000
0"
#595000
b1111 (
1"
#600000
0"
1#
#605000
b0 (
1"
#610000
0"
0#
#615000
b1 (
1"
#620000
0"
#625000
b10 (
1"
#630000
0"
#635000
b11 (
1"
#640000
0"
#645000
b100 (
1"
#650000
0"
#655000
b101 (
1"
#660000
0"
#665000
b110 (
1"
#670000
0"
#675000
b111 (
1"
#680000
0"
#685000
b1000 (
1"
#690000
0"
#695000
b1001 (
1"
#700000
0"
#705000
b1010 (
1"
#710000
0"
#715000
b1011 (
1"
#720000
0"
#725000
b1100 (
1"
#730000
0"
#735000
b1101 (
1"
#740000
0"
#745000
b1110 (
1"
#750000
0"
#755000
b1111 (
1"
#760000
0"
#765000
b10000 (
1"
#770000
0"
#775000
b10001 (
1"
#780000
0"
#785000
b10010 (
1"
#790000
0"
#795000
b10011 (
1"
#800000
0"
#805000
b10100 (
1"
#810000
0"
#815000
1!
b10101 (
1"
#820000
0"
#825000
b10110 (
1"
#830000
0"
#835000
b10111 (
1"
#840000
0!
b0 (
0"
0$
#845000
1"
#850000
0"
#855000
1"
#860000
0"
1$
#865000
b1 (
1"
#870000
0"
#875000
b10 (
1"
#880000
0"
#885000
b11 (
1"
