rtl/debounce.v
// Takes any fault flag from a comparator and ensures it's been active 
// for a minimum number of cycles before passing it to the FSM. Filters single-cycle glitches.
// 
// inputs:  clk, rst_n, fault_in
// outputs: fault_out
// parameters: THRESHOLD, CTR_WIDTH
// 
// Concept is almost identical to wd_timer but inverted logic — counter increments 
// while fault_in is high, resets when it goes low, and fault_out asserts when counter 
// reaches threshold:
// 
// fault_in high → increment counter
// fault_in low  → reset counter to 0
// fault_out     → counter >= THRESHOLD
`timescale 1ns/1ps

module debounce #(
    parameter THRESHOLD = 10,
    parameter CTR_WIDTH = 4
)(
    input wire clk,
    input wire rst_n,
    input wire fault_in,
    output reg fault_out
);

reg [CTR_WIDTH-1: 0] count;

always @(posedge clk or negedge rst_n) begin
    if (!rst_n) begin
        fault_out <= 1'b0;
        count <= 0;
    end else begin
        if (fault_in) begin
            count <= count + 1;
            fault_out <= (count >= THRESHOLD);
        end else begin
            count <= 0;
            fault_out <= 1'b0;
        end
        
    end
end

endmodule

tb/tb_debounce.v
`timescale 1ns/1ps

module tb_debounce;

    // signals to connect to DUT
    reg  clk, rst_n;
    reg  fault_in;
    wire fault_out;

    // instantiate debounce with default parameters
    debounce #(
        .THRESHOLD(10),
        .CTR_WIDTH(4)
    ) DUT (
        .clk       (clk),
        .rst_n     (rst_n),
        .fault_in  (fault_in),
        .fault_out (fault_out)
    );

    initial clk = 0;
    always #5 clk = ~clk; // 10ns period, 100MHz

    initial begin
        $dumpfile("sim/sim_records/tb_debounce.vcd");
        $dumpvars(0, tb_debounce);
    end

    initial begin
        rst_n    = 1'b0;
        fault_in = 1'b0;

        #20 rst_n = 1'b1; // release reset

        // single cycle glitch — should NOT assert fault_out
        #10 fault_in = 1'b1;
        #10 fault_in = 1'b0;

        #20; // settle

        // sustained fault — should assert fault_out after THRESHOLD cycles
        #10 fault_in = 1'b1;
        #150; // hold for 15 cycles, well past threshold of 10

        // fault clears — fault_out should deassert immediately
        fault_in = 1'b0;
        #30;

        // fault asserts again briefly then clears before threshold
        #10 fault_in = 1'b1;
        #50; // 5 cycles — not enough to reach threshold
        fault_in = 1'b0;
        #30;

        // reset during active fault
        #10 fault_in = 1'b1;
        #80; // let fault_out assert
        rst_n = 1'b0; // force reset
        #20 rst_n = 1'b1; // release — fault_out should be 0
        fault_in = 1'b0;
        #30;

        $finish;
    end

endmodule

sim/sim_records/tb_debounce.vcd
$date
	Sat May 23 11:27:15 2026
$end
$version
	Icarus Verilog
$end
$timescale
	1ps
$end
$scope module tb_debounce $end
$var wire 1 ! fault_out $end
$var reg 1 " clk $end
$var reg 1 # fault_in $end
$var reg 1 $ rst_n $end
$scope module DUT $end
$var wire 1 " clk $end
$var wire 1 # fault_in $end
$var wire 1 $ rst_n $end
$var parameter 32 % CTR_WIDTH $end
$var parameter 32 & THRESHOLD $end
$var reg 4 ' count [3:0] $end
$var reg 1 ! fault_out $end
$upscope $end
$upscope $end
$enddefinitions $end
$comment Show the parameter values. $end
$dumpall
b1010 &
b100 %
$end
#0
$dumpvars
b0 '
0$
0#
0"
0!
$end
#5000
1"
#10000
0"
#15000
1"
#20000
0"
1$
#25000
1"
#30000
0"
1#
#35000
b1 '
1"
#40000
0"
0#
#45000
b0 '
1"
#50000
0"
#55000
1"
#60000
0"
#65000
1"
#70000
0"
1#
#75000
b1 '
1"
#80000
0"
#85000
b10 '
1"
#90000
0"
#95000
b11 '
1"
#100000
0"
#105000
b100 '
1"
#110000
0"
#115000
b101 '
1"
#120000
0"
#125000
b110 '
1"
#130000
0"
#135000
b111 '
1"
#140000
0"
#145000
b1000 '
1"
#150000
0"
#155000
b1001 '
1"
#160000
0"
#165000
b1010 '
1"
#170000
0"
#175000
1!
b1011 '
1"
#180000
0"
#185000
b1100 '
1"
#190000
0"
#195000
b1101 '
1"
#200000
0"
#205000
b1110 '
1"
#210000
0"
#215000
b1111 '
1"
#220000
0"
0#
#225000
0!
b0 '
1"
#230000
0"
#235000
1"
#240000
0"
#245000
1"
#250000
0"
#255000
1"
#260000
0"
1#
#265000
b1 '
1"
#270000
0"
#275000
b10 '
1"
#280000
0"
#285000
b11 '
1"
#290000
0"
#295000
b100 '
1"
#300000
0"
#305000
b101 '
1"
#310000
0"
0#
#315000
b0 '
1"
#320000
0"
#325000
1"
#330000
0"
#335000
1"
#340000
0"
#345000
1"
#350000
0"
1#
#355000
b1 '
1"
#360000
0"
#365000
b10 '
1"
#370000
0"
#375000
b11 '
1"
#380000
0"
#385000
b100 '
1"
#390000
0"
#395000
b101 '
1"
#400000
0"
#405000
b110 '
1"
#410000
0"
#415000
b111 '
1"
#420000
0"
#425000
b1000 '
1"
#430000
b0 '
0"
0$
#435000
1"
#440000
0"
#445000
1"
#450000
0"
0#
1$
