rtl/fault_fsm.v
// one sequential block for the state register, one combinational block for next-state logic:
// 
// Block 1: always @(posedge clk) — holds current state
// Block 2: always @(*)           — computes next_state from inputs
// Block 3: always @(*)           — drives outputs from current state
// 
// inputs:  clk, rst_n, oc_a, oc_b, uv_a, ov_a, uv_b, ov_b, ot, hb_fault, mr
// outputs: en_out, health, warn

`timescale 1ns/1ps

module fault_fsm
(
    input wire clk,
    input wire rst_n,
    input wire oc_a,
    input wire oc_b,
    input wire uv_a,
    input wire ov_a,
    input wire uv_b,
    input wire ov_b,
    input wire ot,
    input wire hb_fault,
    input wire mr,
    output reg en_out,
    output reg health,
    output reg warn
);
localparam INIT     = 3'd0;
localparam NORMAL   = 3'd1;
localparam WARN     = 3'd2;
localparam FAULT    = 3'd3;
localparam RECOVERY = 3'd4;

reg [2:0] state;
reg [2:0] next_state;
reg [3:0] warn_count;
reg       latched;

always @(posedge clk or negedge rst_n) begin
    if (!rst_n) begin
        state <= INIT;
        warn_count <= 4'd0;
        latched <= 1'b0;
    end else begin
        state <= next_state;

        // Settling warn_count
        if (next_state == WARN)
            warn_count <= warn_count + 4'd1;
        else
            warn_count <= 4'd0;

        // Settling latching
        if (state == NORMAL && (ov_a || ov_b || hb_fault))
            latched <= 1'b1;
        else if (state == RECOVERY)
            latched <= 1'b0;   
    end
end

always @(*) begin
    next_state = state;
    case (state)
        INIT: begin
            next_state = NORMAL;
        end
        NORMAL: begin
            if (ov_a || ov_b || hb_fault) 
                next_state = FAULT;
            else if (oc_a || oc_b || uv_a || uv_b || ot) begin
                    next_state = WARN;
            end else next_state = NORMAL;
        end
        WARN: begin
            if (ov_a || ov_b || hb_fault || (warn_count >= 4'd10 ))
                next_state = FAULT;
            else if (oc_a || oc_b || uv_a || uv_b || ot)
                next_state = WARN;
            else 
                next_state = NORMAL;
        end
        FAULT: begin
            if ((!(oc_a || oc_b || ov_a || ov_b || uv_a || uv_b || ot || hb_fault)) && (mr || !latched)) begin
                next_state = RECOVERY;         
            end else next_state = FAULT;
        end
        RECOVERY: begin
            if (ov_a || ov_b || hb_fault)
                next_state = FAULT;
            else if (oc_a || oc_b || uv_a || uv_b || ot)
                next_state = WARN;
            else
                next_state = NORMAL;
        end
    endcase
end

always @(*) begin
    en_out = (state == FAULT) ? 1'b0 : 1'b1; 
    health = (state == FAULT) ? 1'b0 : 1'b1; 
    warn   = (state == FAULT || state == WARN) ? 1'b1 : 1'b0;
end

endmodule

rtl/wd_timer.v
// inputs:  clk, rst_n, edge_pulse, timeout_cfg [15:0]
// outputs: hb_fault
// takes edge_pulse from edge_detect and outputs hb_fault to the FSM. 
// Conceptually just a counter that resets on every pulse and faults when it times out.

module wd_timer #(
    parameter WIDTH = 16

)(
    input wire              clk,
    input wire              rst_n,
    input wire              edge_pulse,
    input wire  [WIDTH-1:0] timeout_cfg,
    output reg              hb_fault
);

reg [WIDTH-1:0] count;

always @(posedge clk or negedge rst_n ) begin
    if (!rst_n) begin
        count <= 0;
        hb_fault <= 1'b0;
    end else begin
        if (edge_pulse) begin
            count <= 0;
            hb_fault <= 1'b0;
        end else begin
            count <= count + 1;
            hb_fault <= (count >= timeout_cfg);
        end
    end
end

endmodule

rtl/edge_detect.v
// Edge detector module
// edge_pulse = 1 for one clock cycle during edge transition

module edge_detect
(
    input wire hb_in,
    input wire clk,
    input wire rst_n,
    output reg edge_pulse
);

reg prev_hb;

always @(posedge clk or negedge rst_n) begin
    if (!rst_n) begin
        prev_hb <= 1'b0;
        edge_pulse <= 1'b0;
    end else begin
       prev_hb <= hb_in;
       edge_pulse <= (hb_in != prev_hb); 
    end   
end

endmodule

rtl/debounce.v
// Takes any fault flag from a comparator and ensures it's been active 
// for a minimum number of cycles before passing it to the FSM. Filters single-cycle glitches.
// 
// inputs:  clk, rst_n, fault_in
// outputs: fault_out
// parameters: THRESHOLD, CTR_WIDTH
// 
// Concept is almost identical to wd_timer but inverted logic — counter increments 
// while fault_in is high, resets when it goes low, and fault_out asserts when counter 
// reaches threshold:
// 
// fault_in high → increment counter
// fault_in low  → reset counter to 0
// fault_out     → counter >= THRESHOLD
`timescale 1ns/1ps

module debounce #(
    parameter THRESHOLD = 10,
    parameter CTR_WIDTH = 4
)(
    input wire clk,
    input wire rst_n,
    input wire fault_in,
    output reg fault_out
);

reg [CTR_WIDTH-1: 0] count;

always @(posedge clk or negedge rst_n) begin
    if (!rst_n) begin
        fault_out <= 1'b0;
        count <= 0;
    end else begin
        if (fault_in) begin
            count <= count + 1;
            fault_out <= (count >= THRESHOLD);
        end else begin
            count <= 0;
            fault_out <= 1'b0;
        end
        
    end
end

endmodule

rtl/comparator.v
// Comparator needs to :
// 1. Compare two numbers, one is the input and the other is a threshold value
// 2. Output 1 if the first number is greater than the second, otherwise output 0
// Value: inputs for v_in, v_ref, hyst etc, outputs fault signal
// Vin, Vref, Hyst, Vout
`timescale 1ns/1ps

module comparator #(
    parameter WIDTH = 8
)(
    input wire [WIDTH-1:0] v_in,
    input wire [WIDTH-1:0] v_ref,
    input wire [WIDTH-1:0] hyst,
    input wire             clk,
    input wire             rst_n,
    output reg             fault
);


always @(posedge clk or negedge rst_n) begin
    if (!rst_n) begin // reset state
        fault <= 1'b0;                      // fault recovery forced
    end else begin // non-reset state
        if (fault) begin // fault present
            if (v_in < (v_ref - hyst)) begin
                fault <= 1'b0;              // fault recovered naturally
            end
        end else begin // fault = 0
            if (v_in >= (v_ref)) begin
                fault <= 1'b1;              // fault asserted
            end
        end
    end
end

endmodule

rtl/i2c_slave.v
// I2C module, processes reference signals

module i2c_slave
(
    input  wire        clk,
    input  wire        rst_n,
    input  wire        mode,
    input  wire        scl,
    input  wire        sda,

    // default values in
    input  wire [7:0]  v_ref_oc_a_dflt,
    input  wire [7:0]  v_ref_oc_b_dflt,
    input  wire [7:0]  v_ref_ov_a_dflt,
    input  wire [7:0]  v_ref_ov_b_dflt,
    input  wire [7:0]  v_ref_uv_a_dflt,
    input  wire [7:0]  v_ref_uv_b_dflt,
    input  wire [7:0]  v_ref_ot_dflt,
    input  wire [7:0]  hyst_dflt,
    input  wire [15:0] hb_timeout_dflt,

    // configured values out
    output reg [7:0]  v_ref_oc_a,
    output reg [7:0]  v_ref_oc_b,
    output reg [7:0]  v_ref_ov_a,
    output reg [7:0]  v_ref_ov_b,
    output reg [7:0]  v_ref_uv_a,
    output reg [7:0]  v_ref_uv_b,
    output reg [7:0]  v_ref_ot,
    output reg [7:0]  hyst,
    output reg [15:0] hb_timeout
);

// stub — passthrough regardless of mode
always @(*) begin
    if (mode) begin
        v_ref_oc_a = v_ref_oc_a_dflt;
        v_ref_oc_b = v_ref_oc_b_dflt;
        v_ref_ov_a = v_ref_ov_a_dflt;
        v_ref_ov_b = v_ref_ov_b_dflt;
        v_ref_uv_a = v_ref_uv_a_dflt;
        v_ref_uv_b = v_ref_uv_b_dflt;
        v_ref_ot   = v_ref_ot_dflt;
        hyst       = hyst_dflt;
        hb_timeout = hb_timeout_dflt;
    end else begin
        v_ref_oc_a = v_ref_oc_a_dflt;
        v_ref_oc_b = v_ref_oc_b_dflt;
        v_ref_ov_a = v_ref_ov_a_dflt;
        v_ref_ov_b = v_ref_ov_b_dflt;
        v_ref_uv_a = v_ref_uv_a_dflt;
        v_ref_uv_b = v_ref_uv_b_dflt;
        v_ref_ot   = v_ref_ot_dflt;
        hyst       = hyst_dflt;
        hb_timeout = hb_timeout_dflt;
    end
end

endmodule

rtl/cd1624_top.v
`include "rtl/comparator.v"
`include "rtl/debounce.v"
`include "rtl/edge_detect.v"
`include "rtl/fault_fsm.v"
`include "rtl/wd_timer.v"
`include "rtl/i2c_slave.v"
`timescale 1ns/1ps

module cd1624_top #(
    parameter CLK = 100, // default 100MHz
    parameter V_REF_OC_A  = 8'd200,
    parameter V_REF_OV_A  = 8'd220,
    parameter V_REF_OC_B  = 8'd200,
    parameter V_REF_OV_B  = 8'd220,
    parameter V_REF_UV_A  = 8'd100,
    parameter V_REF_UV_B  = 8'd100,
    parameter V_REF_OT    = 8'd180,
    parameter HYST        = 8'd10,
    parameter HB_TIMEOUT  = 16'd10000
)(
    input wire [7:0] vsen_a,
    input wire [7:0] vsen_b,
    input wire [7:0] isen_a,
    input wire [7:0] isen_b,
    input wire [7:0] tsen,
    input wire       hb,
    input wire       mr,
    input wire       mode,
    input wire       scl,
    input wire       sda,
    input wire       rst_n,
    output wire      health,
    output wire      warn,
    output wire      en_out
);

reg int_clk;
initial int_clk = 0;
always #(CLK/20) int_clk = ~int_clk; // Period is dependent on the clock parameter

// I2C
wire [7:0]  v_ref_oc_a, v_ref_oc_b;
wire [7:0]  v_ref_ov_a, v_ref_ov_b;
wire [7:0]  v_ref_uv_a, v_ref_uv_b;
wire [7:0]  v_ref_ot;
wire [7:0]  hyst;
wire [15:0] hb_timeout;

i2c_slave i2c_slave (
    .clk             (int_clk   ),
    .rst_n           (rst_n     ),
    .mode            (mode      ),
    .sda             (sda       ),
    .scl             (scl       ),
    .v_ref_oc_a_dflt (V_REF_OC_A),
    .v_ref_oc_b_dflt (V_REF_OC_B),
    .v_ref_uv_a_dflt (V_REF_UV_A),
    .v_ref_uv_b_dflt (V_REF_UV_B),
    .v_ref_ov_a_dflt (V_REF_OV_A),
    .v_ref_ov_b_dflt (V_REF_OV_B),
    .v_ref_ot_dflt   (V_REF_OT  ),
    .hyst_dflt       (HYST      ),
    .hb_timeout_dflt (HB_TIMEOUT),
    .v_ref_oc_a      (v_ref_oc_a),
    .v_ref_oc_b      (v_ref_oc_b),
    .v_ref_uv_a      (v_ref_uv_a),
    .v_ref_uv_b      (v_ref_uv_b),
    .v_ref_ov_a      (v_ref_ov_a),
    .v_ref_ov_b      (v_ref_ov_b),
    .v_ref_ot        (v_ref_ot  ),
    .hyst            (hyst      ),
    .hb_timeout      (hb_timeout)
);


// Overcurrent
wire oc_fault_a, oc_fault_b;
wire oc_fault_db_a, oc_fault_db_b;

comparator #(.WIDTH(8)) oc_comp_a (
    .clk   (int_clk),
    .rst_n (rst_n),
    .v_in  (isen_a),
    .v_ref (v_ref_oc_a),
    .hyst  (hyst),
    .fault (oc_fault_a)
);

comparator #(.WIDTH(8)) oc_comp_b (
    .clk   (int_clk),
    .rst_n (rst_n),
    .v_in  (isen_b),
    .v_ref (v_ref_oc_b),
    .hyst  (hyst),
    .fault (oc_fault_b)
);

debounce #(.THRESHOLD(10), .CTR_WIDTH(4)) oc_debounce_a (
    .clk       (int_clk),
    .rst_n     (rst_n),
    .fault_in  (oc_fault_a),
    .fault_out (oc_fault_db_a)
);

debounce #(.THRESHOLD(10), .CTR_WIDTH(4)) oc_debounce_b (
    .clk       (int_clk),
    .rst_n     (rst_n),
    .fault_in  (oc_fault_b),
    .fault_out (oc_fault_db_b)
);

// Overvoltage
wire ov_fault_a, ov_fault_b;
wire ov_fault_db_a, ov_fault_db_b;

comparator #(.WIDTH(8)) ov_comp_a (
    .clk   (int_clk),
    .rst_n (rst_n),
    .v_in  (vsen_a),
    .v_ref (v_ref_ov_a),
    .hyst  (hyst),
    .fault (ov_fault_a)
);

comparator #(.WIDTH(8)) ov_comp_b (
    .clk   (int_clk),
    .rst_n (rst_n),
    .v_in  (vsen_b),
    .v_ref (v_ref_ov_b),
    .hyst  (hyst),
    .fault (ov_fault_b)
);

debounce #(.THRESHOLD(10), .CTR_WIDTH(4)) ov_debounce_a (
    .clk       (int_clk),
    .rst_n     (rst_n),
    .fault_in  (ov_fault_a),
    .fault_out (ov_fault_db_a)
);

debounce #(.THRESHOLD(10), .CTR_WIDTH(4)) ov_debounce_b (
    .clk       (int_clk),
    .rst_n     (rst_n),
    .fault_in  (ov_fault_b),
    .fault_out (ov_fault_db_b)
);

// Undervoltage
wire uv_fault_a, uv_fault_b;
wire uv_fault_db_a, uv_fault_db_b;

comparator #(.WIDTH(8)) uv_comp_a (
    .clk   (int_clk),
    .rst_n (rst_n),
    .v_in  (v_ref_uv_a),
    .v_ref (vsen_a),
    .hyst  (hyst),
    .fault (uv_fault_a)
);

comparator #(.WIDTH(8)) uv_comp_b (
    .clk   (int_clk),
    .rst_n (rst_n),
    .v_in  (v_ref_uv_b),
    .v_ref (vsen_b),
    .hyst  (hyst),
    .fault (uv_fault_b)
);

debounce #(.THRESHOLD(10), .CTR_WIDTH(4)) uv_debounce_a (
    .clk       (int_clk),
    .rst_n     (rst_n),
    .fault_in  (uv_fault_a),
    .fault_out (uv_fault_db_a)
);

debounce #(.THRESHOLD(10), .CTR_WIDTH(4)) uv_debounce_b (
    .clk       (int_clk),
    .rst_n     (rst_n),
    .fault_in  (uv_fault_b),
    .fault_out (uv_fault_db_b)
);

// Temperature
wire ot_fault;
wire ot_fault_db;

comparator #(.WIDTH(8)) t_comp (
    .clk   (int_clk),
    .rst_n (rst_n),
    .v_in  (tsen),
    .v_ref (v_ref_ot),
    .hyst  (hyst),
    .fault (ot_fault)
);

debounce #(.THRESHOLD(10), .CTR_WIDTH(4)) t_debounce (
    .clk       (int_clk),
    .rst_n     (rst_n),
    .fault_in  (ot_fault),
    .fault_out (ot_fault_db)
);

// HB
wire hb_edge;
wire hb_fault;

edge_detect hb_edge_detect (
    .clk        (int_clk),
    .rst_n      (rst_n),
    .hb_in      (hb),
    .edge_pulse (hb_edge)
);

wd_timer #(.WIDTH(16)) hb_wd_timer (
    .clk         (int_clk),
    .rst_n       (rst_n),
    .edge_pulse  (hb_edge),
    .timeout_cfg (hb_timeout),
    .hb_fault    (hb_fault)
);

// Fault FSM
fault_fsm fault_fsm (
    .clk      (int_clk),
    .rst_n    (rst_n),
    .oc_a     (oc_fault_db_a),
    .oc_b     (oc_fault_db_b),
    .uv_a     (uv_fault_db_a),
    .ov_a     (ov_fault_db_a),
    .uv_b     (uv_fault_db_b),
    .ov_b     (ov_fault_db_b),
    .ot       (ot_fault_db),
    .hb_fault (hb_fault),  // No db as wd_timer already detects sustained fault
    .mr       (mr),
    .en_out   (en_out),
    .health   (health),
    .warn     (warn)
);

endmodule

tb/tb_cd1624_top.v
// testbench for top level module


`timescale 1ns/1ps

module tb_cd1624_top;

    // external pin signals
    reg        rst_n;
    reg        mode;
    reg        mr;
    reg        hb;
    reg        scl, sda;
    reg  [7:0] vsen_a, vsen_b;
    reg  [7:0] isen_a, isen_b;
    reg  [7:0] tsen;
    wire       health, warn, en_out;

    // instantiate top level
    cd1624_top #(
        .CLK         (100  ),
        .V_REF_OC_A  (8'd150),
        .V_REF_OC_B  (8'd150),
        .V_REF_OV_A  (8'd200),
        .V_REF_OV_B  (8'd200),
        .V_REF_UV_A  (8'd80 ),
        .V_REF_UV_B  (8'd80 ),
        .V_REF_OT    (8'd180),
        .HYST        (8'd10 ),
        .HB_TIMEOUT  (16'd20)   // small for simulation
    ) DUT (
        .rst_n  (rst_n ),
        .mode   (mode  ),
        .mr     (mr    ),
        .hb     (hb    ),
        .scl    (scl   ),
        .sda    (sda   ),
        .vsen_a (vsen_a),
        .vsen_b (vsen_b),
        .isen_a (isen_a),
        .isen_b (isen_b),
        .tsen   (tsen  ),
        .health (health),
        .warn   (warn  ),
        .en_out (en_out)
    );

    // waveform dump
    initial begin
        $dumpfile("tb_cd1624_top.vcd");
        $dumpvars(0, tb_cd1624_top);
    end

    // heartbeat task — toggles hb at given period for n cycles
    task send_heartbeat;
        input integer n;
        input integer half_period;
        integer i;
        begin
            for (i = 0; i < n; i = i + 1) begin
                #(half_period) hb = ~hb;
            end
        end
    endtask

    // clear all fault inputs
    task healthy_inputs;
        begin
            vsen_a = 8'd150;   // between UV(80) and OV(200) — healthy
            vsen_b = 8'd150;
            isen_a = 8'd100;   // below OC(150) — healthy
            isen_b = 8'd100;
            tsen   = 8'd100;   // below OT(180) — healthy
        end
    endtask

    initial begin
        // initialize
        rst_n  = 1'b0;
        mode   = 1'b0;
        mr     = 1'b0;
        hb     = 1'b0;
        scl    = 1'b0;
        sda    = 1'b1;
        healthy_inputs;

        #40 rst_n = 1'b1;  // release reset
        #20;

        // ── scenario 1: normal powerup ───────────────────────────
        // all inputs healthy, HB toggling — should reach NORMAL
        // health=1, warn=0, en_out=1
        send_heartbeat(10, 20);
        #50;

        // ── scenario 2: overcurrent rail A ──────────────────────
        // isen_a crosses OC threshold — WARN then FAULT
        // warn should assert first, then en_out deasserts
        isen_a = 8'd200;   // above OC threshold of 150
        send_heartbeat(6, 20);
        #200;              // wait for debounce + warn escalation

        // clear OC — auto recover
        isen_a = 8'd100;
        #100;

        // ── scenario 3: overvoltage rail B ──────────────────────
        // immediate fault, no warn — latching
        vsen_b = 8'd220;   // above OV threshold of 200
        send_heartbeat(4, 20);
        #100;

        // OV clears — should stay in FAULT (latched)
        vsen_b = 8'd150;
        #100;

        // assert MR — should recover
        mr = 1'b1;
        #20 mr = 1'b0;
        #50;

        // ── scenario 4: undervoltage rail A ─────────────────────
        // vsen_a drops below UV threshold — WARN then FAULT
        vsen_a = 8'd50;    // below UV threshold of 80
        send_heartbeat(6, 20);
        #200;

        // voltage recovers — auto recover
        vsen_a = 8'd150;
        #100;

        // ── scenario 5: overtemperature ─────────────────────────
        // tsen crosses OT threshold — WARN then FAULT
        tsen = 8'd200;     // above OT threshold of 180
        send_heartbeat(6, 20);
        #200;

        // temperature recovers
        tsen = 8'd100;
        #100;

        // ── scenario 6: missing heartbeat ───────────────────────
        // stop toggling HB — wd_timer times out after HB_TIMEOUT=20 cycles
        // immediate FAULT, latching
        healthy_inputs;
        #500;              // well past HB_TIMEOUT of 20 cycles

        // heartbeat resumes + MR to recover
        send_heartbeat(4, 20);
        mr = 1'b1;
        #20 mr = 1'b0;
        #50;

        // ── scenario 7: multiple simultaneous faults ─────────────
        isen_a = 8'd200;   // OC
        vsen_b = 8'd50;    // UV on rail B
        send_heartbeat(6, 20);
        #200;

        isen_a = 8'd100;
        vsen_b = 8'd150;
        #100;

        // ── scenario 8: reset during fault ──────────────────────
        vsen_a = 8'd220;   // OV — immediate fault
        send_heartbeat(4, 20);
        #100;
        rst_n = 1'b0;
        #40 rst_n = 1'b1;
        vsen_a = 8'd150;
        send_heartbeat(4, 20);
        #100;

        $finish;
    end

endmodule

sim_records/tb_cd1624_top_test2.vcd
$date
	Sun May 24 16:03:29 2026
$end
$version
	Icarus Verilog
$end
$timescale
	1ps
$end
$scope module tb_cd1624_top $end
$var wire 1 ! warn $end
$var wire 1 " health $end
$var wire 1 # en_out $end
$var reg 1 $ hb $end
$var reg 8 % isen_a [7:0] $end
$var reg 8 & isen_b [7:0] $end
$var reg 1 ' mode $end
$var reg 1 ( mr $end
$var reg 1 ) rst_n $end
$var reg 1 * scl $end
$var reg 1 + sda $end
$var reg 8 , tsen [7:0] $end
$var reg 8 - vsen_a [7:0] $end
$var reg 8 . vsen_b [7:0] $end
$scope module DUT $end
$var wire 1 $ hb $end
$var wire 8 / isen_a [7:0] $end
$var wire 8 0 isen_b [7:0] $end
$var wire 1 ' mode $end
$var wire 1 ( mr $end
$var wire 1 ) rst_n $end
$var wire 1 * scl $end
$var wire 1 + sda $end
$var wire 8 1 tsen [7:0] $end
$var wire 8 2 vsen_a [7:0] $end
$var wire 8 3 vsen_b [7:0] $end
$var wire 1 ! warn $end
$var wire 8 4 v_ref_uv_b [7:0] $end
$var wire 8 5 v_ref_uv_a [7:0] $end
$var wire 8 6 v_ref_ov_b [7:0] $end
$var wire 8 7 v_ref_ov_a [7:0] $end
$var wire 8 8 v_ref_ot [7:0] $end
$var wire 8 9 v_ref_oc_b [7:0] $end
$var wire 8 : v_ref_oc_a [7:0] $end
$var wire 1 ; uv_fault_db_b $end
$var wire 1 < uv_fault_db_a $end
$var wire 1 = uv_fault_b $end
$var wire 1 > uv_fault_a $end
$var wire 1 ? ov_fault_db_b $end
$var wire 1 @ ov_fault_db_a $end
$var wire 1 A ov_fault_b $end
$var wire 1 B ov_fault_a $end
$var wire 1 C ot_fault_db $end
$var wire 1 D ot_fault $end
$var wire 1 E oc_fault_db_b $end
$var wire 1 F oc_fault_db_a $end
$var wire 1 G oc_fault_b $end
$var wire 1 H oc_fault_a $end
$var wire 8 I hyst [7:0] $end
$var wire 1 " health $end
$var wire 16 J hb_timeout [15:0] $end
$var wire 1 K hb_fault $end
$var wire 1 L hb_edge $end
$var wire 1 # en_out $end
$var parameter 32 M CLK $end
$var parameter 16 N HB_TIMEOUT $end
$var parameter 8 O HYST $end
$var parameter 8 P V_REF_OC_A $end
$var parameter 8 Q V_REF_OC_B $end
$var parameter 8 R V_REF_OT $end
$var parameter 8 S V_REF_OV_A $end
$var parameter 8 T V_REF_OV_B $end
$var parameter 8 U V_REF_UV_A $end
$var parameter 8 V V_REF_UV_B $end
$var reg 1 W int_clk $end
$scope module fault_fsm $end
$var wire 1 W clk $end
$var wire 1 ( mr $end
$var wire 1 ) rst_n $end
$var wire 1 ; uv_b $end
$var wire 1 < uv_a $end
$var wire 1 ? ov_b $end
$var wire 1 @ ov_a $end
$var wire 1 C ot $end
$var wire 1 E oc_b $end
$var wire 1 F oc_a $end
$var wire 1 K hb_fault $end
$var parameter 3 X FAULT $end
$var parameter 3 Y INIT $end
$var parameter 3 Z NORMAL $end
$var parameter 3 [ RECOVERY $end
$var parameter 3 \ WARN $end
$var reg 1 # en_out $end
$var reg 1 " health $end
$var reg 1 ] latched $end
$var reg 3 ^ next_state [2:0] $end
$var reg 3 _ state [2:0] $end
$var reg 1 ! warn $end
$var reg 4 ` warn_count [3:0] $end
$upscope $end
$scope module hb_edge_detect $end
$var wire 1 W clk $end
$var wire 1 $ hb_in $end
$var wire 1 ) rst_n $end
$var reg 1 L edge_pulse $end
$var reg 1 a prev_hb $end
$upscope $end
$scope module hb_wd_timer $end
$var wire 1 W clk $end
$var wire 1 L edge_pulse $end
$var wire 1 ) rst_n $end
$var wire 16 b timeout_cfg [15:0] $end
$var parameter 32 c WIDTH $end
$var reg 16 d count [15:0] $end
$var reg 1 K hb_fault $end
$upscope $end
$scope module i2c_slave $end
$var wire 1 W clk $end
$var wire 16 e hb_timeout_dflt [15:0] $end
$var wire 8 f hyst_dflt [7:0] $end
$var wire 1 ' mode $end
$var wire 1 ) rst_n $end
$var wire 1 * scl $end
$var wire 1 + sda $end
$var wire 8 g v_ref_oc_a_dflt [7:0] $end
$var wire 8 h v_ref_oc_b_dflt [7:0] $end
$var wire 8 i v_ref_ot_dflt [7:0] $end
$var wire 8 j v_ref_ov_a_dflt [7:0] $end
$var wire 8 k v_ref_ov_b_dflt [7:0] $end
$var wire 8 l v_ref_uv_a_dflt [7:0] $end
$var wire 8 m v_ref_uv_b_dflt [7:0] $end
$var reg 16 n hb_timeout [15:0] $end
$var reg 8 o hyst [7:0] $end
$var reg 8 p v_ref_oc_a [7:0] $end
$var reg 8 q v_ref_oc_b [7:0] $end
$var reg 8 r v_ref_ot [7:0] $end
$var reg 8 s v_ref_ov_a [7:0] $end
$var reg 8 t v_ref_ov_b [7:0] $end
$var reg 8 u v_ref_uv_a [7:0] $end
$var reg 8 v v_ref_uv_b [7:0] $end
$upscope $end
$scope module oc_comp_a $end
$var wire 1 W clk $end
$var wire 8 w hyst [7:0] $end
$var wire 1 ) rst_n $end
$var wire 8 x v_in [7:0] $end
$var wire 8 y v_ref [7:0] $end
$var parameter 32 z WIDTH $end
$var reg 1 H fault $end
$upscope $end
$scope module oc_comp_b $end
$var wire 1 W clk $end
$var wire 8 { hyst [7:0] $end
$var wire 1 ) rst_n $end
$var wire 8 | v_in [7:0] $end
$var wire 8 } v_ref [7:0] $end
$var parameter 32 ~ WIDTH $end
$var reg 1 G fault $end
$upscope $end
$scope module oc_debounce_a $end
$var wire 1 W clk $end
$var wire 1 H fault_in $end
$var wire 1 ) rst_n $end
$var parameter 32 !" CTR_WIDTH $end
$var parameter 32 "" THRESHOLD $end
$var reg 4 #" count [3:0] $end
$var reg 1 F fault_out $end
$upscope $end
$scope module oc_debounce_b $end
$var wire 1 W clk $end
$var wire 1 G fault_in $end
$var wire 1 ) rst_n $end
$var parameter 32 $" CTR_WIDTH $end
$var parameter 32 %" THRESHOLD $end
$var reg 4 &" count [3:0] $end
$var reg 1 E fault_out $end
$upscope $end
$scope module ov_comp_a $end
$var wire 1 W clk $end
$var wire 8 '" hyst [7:0] $end
$var wire 1 ) rst_n $end
$var wire 8 (" v_in [7:0] $end
$var wire 8 )" v_ref [7:0] $end
$var parameter 32 *" WIDTH $end
$var reg 1 B fault $end
$upscope $end
$scope module ov_comp_b $end
$var wire 1 W clk $end
$var wire 8 +" hyst [7:0] $end
$var wire 1 ) rst_n $end
$var wire 8 ," v_in [7:0] $end
$var wire 8 -" v_ref [7:0] $end
$var parameter 32 ." WIDTH $end
$var reg 1 A fault $end
$upscope $end
$scope module ov_debounce_a $end
$var wire 1 W clk $end
$var wire 1 B fault_in $end
$var wire 1 ) rst_n $end
$var parameter 32 /" CTR_WIDTH $end
$var parameter 32 0" THRESHOLD $end
$var reg 4 1" count [3:0] $end
$var reg 1 @ fault_out $end
$upscope $end
$scope module ov_debounce_b $end
$var wire 1 W clk $end
$var wire 1 A fault_in $end
$var wire 1 ) rst_n $end
$var parameter 32 2" CTR_WIDTH $end
$var parameter 32 3" THRESHOLD $end
$var reg 4 4" count [3:0] $end
$var reg 1 ? fault_out $end
$upscope $end
$scope module t_comp $end
$var wire 1 W clk $end
$var wire 8 5" hyst [7:0] $end
$var wire 1 ) rst_n $end
$var wire 8 6" v_in [7:0] $end
$var wire 8 7" v_ref [7:0] $end
$var parameter 32 8" WIDTH $end
$var reg 1 D fault $end
$upscope $end
$scope module t_debounce $end
$var wire 1 W clk $end
$var wire 1 D fault_in $end
$var wire 1 ) rst_n $end
$var parameter 32 9" CTR_WIDTH $end
$var parameter 32 :" THRESHOLD $end
$var reg 4 ;" count [3:0] $end
$var reg 1 C fault_out $end
$upscope $end
$scope module uv_comp_a $end
$var wire 1 W clk $end
$var wire 8 <" hyst [7:0] $end
$var wire 1 ) rst_n $end
$var wire 8 =" v_in [7:0] $end
$var wire 8 >" v_ref [7:0] $end
$var parameter 32 ?" WIDTH $end
$var reg 1 > fault $end
$upscope $end
$scope module uv_comp_b $end
$var wire 1 W clk $end
$var wire 8 @" hyst [7:0] $end
$var wire 1 ) rst_n $end
$var wire 8 A" v_in [7:0] $end
$var wire 8 B" v_ref [7:0] $end
$var parameter 32 C" WIDTH $end
$var reg 1 = fault $end
$upscope $end
$scope module uv_debounce_a $end
$var wire 1 W clk $end
$var wire 1 > fault_in $end
$var wire 1 ) rst_n $end
$var parameter 32 D" CTR_WIDTH $end
$var parameter 32 E" THRESHOLD $end
$var reg 4 F" count [3:0] $end
$var reg 1 < fault_out $end
$upscope $end
$scope module uv_debounce_b $end
$var wire 1 W clk $end
$var wire 1 = fault_in $end
$var wire 1 ) rst_n $end
$var parameter 32 G" CTR_WIDTH $end
$var parameter 32 H" THRESHOLD $end
$var reg 4 I" count [3:0] $end
$var reg 1 ; fault_out $end
$upscope $end
$upscope $end
$scope task healthy_inputs $end
$upscope $end
$scope task send_heartbeat $end
$var integer 32 J" half_period [31:0] $end
$var integer 32 K" i [31:0] $end
$var integer 32 L" n [31:0] $end
$upscope $end
$upscope $end
$enddefinitions $end
$comment Show the parameter values. $end
$dumpall
b1010 H"
b100 G"
b1010 E"
b100 D"
b1000 C"
b1000 ?"
b1010 :"
b100 9"
b1000 8"
b1010 3"
b100 2"
b1010 0"
b100 /"
b1000 ."
b1000 *"
b1010 %"
b100 $"
b1010 ""
b100 !"
b1000 ~
b1000 z
b10000 c
b10 \
b100 [
b1 Z
b0 Y
b11 X
b1010000 V
b1010000 U
b11001000 T
b11001000 S
b10110100 R
b10010110 Q
b10010110 P
b1010 O
b10100 N
b1100100 M
$end
#0
$dumpvars
bx L"
bx K"
bx J"
b0 I"
b0 F"
b10010110 B"
b1010000 A"
b1010 @"
b10010110 >"
b1010000 ="
b1010 <"
b0 ;"
b10110100 7"
b1100100 6"
b1010 5"
b0 4"
b0 1"
b11001000 -"
b10010110 ,"
b1010 +"
b11001000 )"
b10010110 ("
b1010 '"
b0 &"
b0 #"
b10010110 }
b1100100 |
b1010 {
b10010110 y
b1100100 x
b1010 w
b1010000 v
b1010000 u
b11001000 t
b11001000 s
b10110100 r
b10010110 q
b10010110 p
b1010 o
b10100 n
b1010000 m
b1010000 l
b11001000 k
b11001000 j
b10110100 i
b10010110 h
b10010110 g
b1010 f
b10100 e
b0 d
b10100 b
0a
b0 `
b0 _
b1 ^
0]
0W
0L
0K
b10100 J
b1010 I
0H
0G
0F
0E
0D
0C
0B
0A
0@
0?
0>
0=
0<
0;
b10010110 :
b10010110 9
b10110100 8
b11001000 7
b11001000 6
b1010000 5
b1010000 4
b10010110 3
b10010110 2
b1100100 1
b1100100 0
b1100100 /
b10010110 .
b10010110 -
b1100100 ,
1+
0*
0)
0(
0'
b1100100 &
b1100100 %
0$
1#
1"
0!
$end
#5000
1W
#10000
0W
#15000
1W
#20000
0W
#25000
1W
#30000
0W
#35000
1W
#40000
0W
1)
#45000
b1 _
b1 d
1W
#50000
0W
#55000
b10 d
1W
#60000
0W
b0 K"
b10100 J"
b1010 L"
#65000
b11 d
1W
#70000
0W
#75000
b100 d
1W
#80000
0W
b1 K"
1$
#85000
b101 d
1L
1a
1W
#90000
0W
#95000
0L
b0 d
1W
#100000
0W
b10 K"
0$
#105000
b1 d
1L
0a
1W
#110000
0W
#115000
0L
b0 d
1W
#120000
0W
b11 K"
1$
#125000
b1 d
1L
1a
1W
#130000
0W
#135000
0L
b0 d
1W
#140000
0W
b100 K"
0$
#145000
b1 d
1L
0a
1W
#150000
0W
#155000
0L
b0 d
1W
#160000
0W
b101 K"
1$
#165000
b1 d
1L
1a
1W
#170000
0W
#175000
0L
b0 d
1W
