rtl/edge_detect.v
// Edge detector module
// edge_pulse = 1 for one clock cycle during edge transition

module edge_detect
(
    input wire hb_in,
    input wire clk,
    input wire rst_n,
    output reg edge_pulse
);

reg prev_hb;

always @(posedge clk or negedge rst_n) begin
    if (!rst_n) begin
        prev_hb <= 1'b0;
        edge_pulse <= 1'b0;
    end else begin
       prev_hb <= hb_in;
       edge_pulse <= (hb_in != prev_hb); 
    end   
end

endmodule

tb/tb_edge_detect.v
`timescale 1ns/1ps

module tb_edge_detect;

    // signals to connect to DUT
    reg  clk, rst_n;
    reg  hb_in;
    wire edge_pulse;

    // instantiate edge_detect
    edge_detect DUT (
        .clk        (clk),
        .rst_n      (rst_n),
        .hb_in      (hb_in),
        .edge_pulse (edge_pulse)
    );

    initial clk = 0;
    always #5 clk = ~clk; // 10ns period, 100MHz

    initial begin
        $dumpfile("sim_records/tb_edge_detect.vcd");
        $dumpvars(0, tb_edge_detect);
    end

    initial begin
        rst_n = 1'b0;
        hb_in = 1'b0;

        #20 rst_n = 1'b1; // release reset

        // hold low — no edge, no pulse
        #50;

        // rising edge — pulse should fire for exactly one cycle
        #10 hb_in = 1'b1;
        #30;

        // hold high — no pulse while held
        #50;

        // falling edge — pulse should fire for exactly one cycle
        #10 hb_in = 1'b0;
        #30;

        // normal square wave — pulse on every transition
        #10 hb_in = 1'b1;
        #20 hb_in = 1'b0;
        #20 hb_in = 1'b1;
        #20 hb_in = 1'b0;
        #20;

        // rapid toggle every cycle — pulse every cycle
        #10 hb_in = 1'b1;
        #10 hb_in = 1'b0;
        #10 hb_in = 1'b1;
        #10 hb_in = 1'b0;
        #20;

        // reset during active toggle — no spurious pulse on release
        #10 hb_in = 1'b1;
        #10 rst_n = 1'b0;
        #20 rst_n = 1'b1;
        #30;

        $finish;
    end

endmodule

sim_records/tb_edge_detect.vcd
$date
	Sat May 23 11:29:25 2026
$end
$version
	Icarus Verilog
$end
$timescale
	1ps
$end
$scope module tb_edge_detect $end
$var wire 1 ! edge_pulse $end
$var reg 1 " clk $end
$var reg 1 # hb_in $end
$var reg 1 $ rst_n $end
$scope module DUT $end
$var wire 1 " clk $end
$var wire 1 # hb_in $end
$var wire 1 $ rst_n $end
$var reg 1 ! edge_pulse $end
$var reg 1 % prev_hb $end
$upscope $end
$upscope $end
$enddefinitions $end
$comment Show the parameter values. $end
$dumpall
$end
#0
$dumpvars
0%
0$
0#
0"
0!
$end
#5000
1"
#10000
0"
#15000
1"
#20000
0"
1$
#25000
1"
#30000
0"
#35000
1"
#40000
0"
#45000
1"
#50000
0"
#55000
1"
#60000
0"
#65000
1"
#70000
0"
#75000
1"
#80000
0"
1#
#85000
1!
1%
1"
#90000
0"
#95000
0!
1"
#100000
0"
#105000
1"
#110000
0"
#115000
1"
#120000
0"
#125000
1"
#130000
0"
#135000
1"
#140000
0"
#145000
1"
#150000
0"
#155000
1"
#160000
0"
#165000
1"
#170000
0"
0#
#175000
1!
0%
1"
#180000
0"
#185000
0!
1"
#190000
0"
#195000
1"
#200000
0"
#205000
1"
#210000
0"
1#
#215000
1!
1%
1"
#220000
0"
#225000
0!
1"
#230000
0"
0#
#235000
1!
0%
1"
#240000
0"
#245000
0!
1"
#250000
0"
1#
#255000
1!
1%
1"
#260000
0"
#265000
0!
1"
#270000
0"
0#
#275000
1!
0%
1"
#280000
0"
#285000
0!
1"
#290000
0"
#295000
1"
#300000
0"
1#
#305000
1!
1%
1"
#310000
0"
0#
#315000
0%
1"
#320000
0"
1#
#325000
1%
1"
#330000
0"
0#
#335000
0%
1"
#340000
0"
#345000
0!
1"
#350000
0"
#355000
1"
#360000
0"
1#
#365000
1!
1%
1"
#370000
0!
0%
0"
0$
#375000
1"
#380000
0"
#385000
1"
#390000
0"
1$
#395000
1!
1%
1"
#400000
0"
#405000
0!
1"
