rtl/fault_fsm.v
// one sequential block for the state register, one combinational block for next-state logic:
// 
// Block 1: always @(posedge clk) — holds current state
// Block 2: always @(*)           — computes next_state from inputs
// Block 3: always @(*)           — drives outputs from current state
// 
// inputs:  clk, rst_n, oc_a, oc_b, uv_a, ov_a, uv_b, ov_b, ot, hb_fault, mr
// outputs: en_out, health, warn

`timescale 1ns/1ps

module fault_fsm
(
    input wire clk,
    input wire rst_n,
    input wire oc_a,
    input wire oc_b,
    input wire uv_a,
    input wire ov_a,
    input wire uv_b,
    input wire ov_b,
    input wire ot,
    input wire hb_fault,
    input wire mr,
    output reg en_out,
    output reg health,
    output reg warn
);
localparam INIT     = 3'd0;
localparam NORMAL   = 3'd1;
localparam WARN     = 3'd2;
localparam FAULT    = 3'd3;
localparam RECOVERY = 3'd4;

reg [2:0] state;
reg [2:0] next_state;
reg [3:0] warn_count;
reg       latched;

always @(posedge clk or negedge rst_n) begin
    if (!rst_n) begin
        state <= INIT;
        warn_count <= 4'd0;
        latched <= 1'b0;
    end else begin
        state <= next_state;

        // Settling warn_count
        if (next_state == WARN)
            warn_count <= warn_count + 4'd1;
        else
            warn_count <= 4'd0;

        // Settling latching
        if (state == NORMAL && (ov_a || ov_b || hb_fault))
            latched <= 1'b1;
        else if (state == RECOVERY)
            latched <= 1'b0;   
    end
end

always @(*) begin
    next_state = state;
    case (state)
        INIT: begin
            next_state = NORMAL;
        end
        NORMAL: begin
            if (ov_a || ov_b || hb_fault) 
                next_state = FAULT;
            else if (oc_a || oc_b || uv_a || uv_b || ot) begin
                    next_state = WARN;
            end else next_state = NORMAL;
        end
        WARN: begin
            if (ov_a || ov_b || hb_fault || (warn_count >= 4'd10 ))
                next_state = FAULT;
            else if (oc_a || oc_b || uv_a || uv_b || ot)
                next_state = WARN;
            else 
                next_state = NORMAL;
        end
        FAULT: begin
            if ((!(oc_a || oc_b || ov_a || ov_b || uv_a || uv_b || ot || hb_fault)) && (mr || !latched)) begin
                next_state = RECOVERY;         
            end else next_state = FAULT;
        end
        RECOVERY: begin
            if (ov_a || ov_b || hb_fault)
                next_state = FAULT;
            else if (oc_a || oc_b || uv_a || uv_b || ot)
                next_state = WARN;
            else
                next_state = NORMAL;
        end
    endcase
end

always @(*) begin
    en_out = (state == FAULT) ? 1'b0 : 1'b1; 
    health = (state == FAULT) ? 1'b0 : 1'b1; 
    warn   = (state == FAULT || state == WARN) ? 1'b1 : 1'b0;
end

endmodule

tb/tb_fault_fsm.v
`timescale 1ns/1ps

module tb_fault_fsm;

    // signals to connect to DUT
    reg  clk, rst_n;
    reg  oc_a, oc_b;
    reg  uv_a, uv_b;
    reg  ov_a, ov_b;
    reg  ot;
    reg  hb_fault;
    reg  mr;
    wire en_out, health, warn;

    // instantiate fault_fsm
    fault_fsm DUT (
        .clk      (clk),
        .rst_n    (rst_n),
        .oc_a     (oc_a),
        .oc_b     (oc_b),
        .uv_a     (uv_a),
        .uv_b     (uv_b),
        .ov_a     (ov_a),
        .ov_b     (ov_b),
        .ot       (ot),
        .hb_fault (hb_fault),
        .mr       (mr),
        .en_out   (en_out),
        .health   (health),
        .warn     (warn)
    );

    initial clk = 0;
    always #5 clk = ~clk; // 10ns period, 100MHz

    initial begin
        $dumpfile("sim_records/tb_fault_fsm.vcd");
        $dumpvars(0, tb_fault_fsm);
    end

    // task to clear all fault inputs cleanly
    task clear_all;
        begin
            oc_a = 0; oc_b = 0;
            uv_a = 0; uv_b = 0;
            ov_a = 0; ov_b = 0;
            ot   = 0; hb_fault = 0;
            mr   = 0;
        end
    endtask

    initial begin
        // initialize
        rst_n = 1'b0;
        clear_all;

        #20 rst_n = 1'b1;
        #20; // settle through INIT into NORMAL

        // scenario 1: normal powerup
        // should be INIT → NORMAL, en_out=1 health=1 warn=0
        #20;

        // scenario 2: OV immediate fault (latching)
        // NORMAL → FAULT immediately, no WARN
        // en_out and health should deassert, warn should assert
        #10 ov_a = 1'b1;
        #30;

        // OV clears — should stay in FAULT (latched), needs MR
        ov_a = 1'b0;
        #40;

        // assert MR — should go to RECOVERY then NORMAL
        mr = 1'b1;
        #10 mr = 1'b0;
        #20;

        // scenario 3: UV warn escalation
        // NORMAL → WARN → FAULT after 10 cycles
        // warn should assert in WARN state
        #10 uv_a = 1'b1;
        #150; // hold for 15 cycles, past warn threshold of 10

        // fault clears — auto recover (not latching)
        uv_a = 1'b0;
        #20;
        // no MR needed — should auto recover to NORMAL
        #20;

        // scenario 4: UV clears during WARN
        // should return to NORMAL without reaching FAULT
        #10 uv_b = 1'b1;
        #50; // 5 cycles — under threshold
        uv_b = 1'b0;
        #30; // should be back in NORMAL

        // scenario 5: HB fault (latching, immediate)
        // NORMAL → FAULT immediately, requires MR
        #10 hb_fault = 1'b1;
        #30;
        hb_fault = 1'b0;
        #30; // stays in FAULT without MR

        mr = 1'b1;
        #10 mr = 1'b0;
        #20; // RECOVERY → NORMAL

        // scenario 6: multiple simultaneous faults
        // OC + UV together — both warn level
        // should enter WARN then escalate to FAULT
        #10 oc_a = 1'b1;
            uv_a = 1'b1;
        #150; // escalate to FAULT
        oc_a = 1'b0;
        uv_a = 1'b0;
        #20; // auto recover
        #20;

        // scenario 7: fault during RECOVERY
        // new fault appears during RECOVERY — should drop back to FAULT
        #10 oc_b = 1'b1;
        #150; // reach FAULT
        oc_b = 1'b0;
        #10; // auto recover starts
        ov_b = 1'b1; // new immediate fault during RECOVERY
        #20;
        ov_b = 1'b0;
        #20;
        mr = 1'b1;
        #10 mr = 1'b0;
        #20;

        // scenario 8: reset during fault
        #10 ov_a = 1'b1;
        #30;
        rst_n = 1'b0; // force reset mid fault
        #20 rst_n = 1'b1;
        ov_a = 1'b0;
        #30; // should be back in INIT → NORMAL cleanly

        $finish;
    end

endmodule

sim_records/tb_fault_fsm.vcd
$date
	Sun May 24 15:38:23 2026
$end
$version
	Icarus Verilog
$end
$timescale
	1ps
$end
$scope module tb_fault_fsm $end
$var wire 1 ! warn $end
$var wire 1 " health $end
$var wire 1 # en_out $end
$var reg 1 $ clk $end
$var reg 1 % hb_fault $end
$var reg 1 & mr $end
$var reg 1 ' oc_a $end
$var reg 1 ( oc_b $end
$var reg 1 ) ot $end
$var reg 1 * ov_a $end
$var reg 1 + ov_b $end
$var reg 1 , rst_n $end
$var reg 1 - uv_a $end
$var reg 1 . uv_b $end
$scope module DUT $end
$var wire 1 $ clk $end
$var wire 1 % hb_fault $end
$var wire 1 & mr $end
$var wire 1 ' oc_a $end
$var wire 1 ( oc_b $end
$var wire 1 ) ot $end
$var wire 1 * ov_a $end
$var wire 1 + ov_b $end
$var wire 1 , rst_n $end
$var wire 1 - uv_a $end
$var wire 1 . uv_b $end
$var parameter 3 / FAULT $end
$var parameter 3 0 INIT $end
$var parameter 3 1 NORMAL $end
$var parameter 3 2 RECOVERY $end
$var parameter 3 3 WARN $end
$var reg 1 # en_out $end
$var reg 1 " health $end
$var reg 1 4 latched $end
$var reg 3 5 next_state [2:0] $end
$var reg 3 6 state [2:0] $end
$var reg 1 ! warn $end
$var reg 4 7 warn_count [3:0] $end
$upscope $end
$scope task clear_all $end
$upscope $end
$upscope $end
$enddefinitions $end
$comment Show the parameter values. $end
$dumpall
b10 3
b100 2
b1 1
b0 0
b11 /
$end
#0
$dumpvars
b0 7
b0 6
b1 5
04
0.
0-
0,
0+
0*
0)
0(
0'
0&
0%
0$
1#
1"
0!
$end
#5000
1$
#10000
0$
#15000
1$
#20000
0$
1,
#25000
b1 6
1$
#30000
0$
#35000
1$
#40000
0$
#45000
1$
#50000
0$
#55000
1$
#60000
0$
#65000
1$
#70000
b11 5
0$
1*
#75000
1!
0"
0#
14
b11 6
1$
#80000
0$
#85000
1$
#90000
0$
#95000
1$
#100000
0$
0*
#105000
1$
#110000
0$
#115000
1$
#120000
0$
#125000
1$
#130000
0$
#135000
1$
#140000
b100 5
0$
1&
#145000
0!
1"
1#
b1 5
b100 6
1$
#150000
b1 5
0$
0&
#155000
04
b1 6
1$
#160000
0$
#165000
1$
#170000
0$
#175000
1$
#180000
b10 5
0$
1-
#185000
1!
b1 7
b10 6
1$
#190000
0$
#195000
b10 7
1$
#200000
0$
#205000
b11 7
1$
#210000
0$
#215000
b100 7
1$
#220000
0$
#225000
b101 7
1$
#230000
0$
#235000
b110 7
1$
#240000
0$
#245000
b111 7
1$
#250000
0$
#255000
b1000 7
1$
#260000
0$
#265000
b1001 7
1$
#270000
0$
#275000
b11 5
b1010 7
1$
#280000
0$
#285000
0"
0#
b0 7
b11 6
1$
#290000
0$
#295000
1$
#300000
0$
#305000
1$
#310000
0$
#315000
1$
#320000
0$
#325000
1$
#330000
b100 5
0$
0-
#335000
0!
1"
1#
b1 5
b100 6
1$
#340000
0$
#345000
b1 6
1$
#350000
0$
#355000
1$
#360000
0$
#365000
1$
#370000
0$
#375000
1$
#380000
b10 5
0$
1.
#385000
1!
b1 7
b10 6
1$
#390000
0$
#395000
b10 7
1$
#400000
0$
#405000
b11 7
1$
#410000
0$
#415000
b100 7
1$
#420000
0$
#425000
b101 7
1$
#430000
b1 5
0$
0.
#435000
0!
b0 7
b1 6
1$
#440000
0$
#445000
1$
#450000
0$
#455000
1$
#460000
0$
#465000
1$
#470000
b11 5
0$
1%
#475000
1!
0"
0#
14
b11 6
1$
#480000
0$
#485000
1$
#490000
0$
#495000
1$
#500000
0$
0%
#505000
1$
#510000
0$
#515000
1$
#520000
0$
#525000
1$
#530000
b100 5
0$
1&
#535000
0!
1"
1#
b1 5
b100 6
1$
#540000
b1 5
0$
0&
#545000
04
b1 6
1$
#550000
0$
#555000
1$
#560000
0$
#565000
1$
#570000
b10 5
0$
1-
1'
#575000
1!
b1 7
b10 6
1$
#580000
0$
#585000
b10 7
1$
#590000
0$
#595000
b11 7
1$
#600000
0$
#605000
b100 7
1$
#610000
0$
#615000
b101 7
1$
#620000
0$
#625000
b110 7
1$
#630000
0$
#635000
b111 7
1$
#640000
0$
#645000
b1000 7
1$
#650000
0$
#655000
b1001 7
1$
#660000
0$
#665000
b11 5
b1010 7
1$
#670000
0$
#675000
0"
0#
b0 7
b11 6
1$
#680000
0$
#685000
1$
#690000
0$
#695000
1$
#700000
0$
#705000
1$
#710000
0$
#715000
1$
#720000
b100 5
0$
0-
0'
#725000
0!
1"
1#
b1 5
b100 6
1$
#730000
0$
#735000
b1 6
1$
#740000
0$
#745000
1$
#750000
0$
#755000
1$
#760000
0$
#765000
1$
#770000
b10 5
0$
1(
#775000
1!
b1 7
b10 6
1$
#780000
0$
#785000
b10 7
1$
#790000
0$
#795000
b11 7
1$
#800000
0$
#805000
b100 7
1$
#810000
0$
#815000
b101 7
1$
#820000
0$
#825000
b110 7
1$
#830000
0$
#835000
b111 7
1$
#840000
0$
#845000
b1000 7
1$
#850000
0$
#855000
b1001 7
1$
#860000
0$
#865000
b11 5
b1010 7
1$
#870000
0$
#875000
0"
0#
b0 7
b11 6
1$
#880000
0$
#885000
1$
#890000
0$
#895000
1$
#900000
0$
#905000
1$
#910000
0$
#915000
1$
#920000
b100 5
0$
0(
#925000
0!
1"
1#
b1 5
b100 6
1$
#930000
b11 5
0$
1+
#935000
1!
0"
0#
b11 6
1$
#940000
0$
#945000
1$
#950000
b100 5
0$
0+
#955000
0!
1"
1#
b1 5
b100 6
1$
#960000
0$
#965000
b1 6
1$
#970000
0$
1&
#975000
1$
#980000
0$
0&
#985000
1$
#990000
0$
#995000
1$
#1000000
0$
#1005000
1$
#1010000
b11 5
0$
1*
#1015000
1!
0"
0#
14
b11 6
1$
#1020000
0$
#1025000
1$
#1030000
0$
#1035000
1$
#1040000
0!
1"
1#
b1 5
04
b0 6
0$
0,
#1045000
1$
#1050000
0$
#1055000
1$
#1060000
b1 5
0$
0*
1,
#1065000
b1 6
1$
